[
    {
        "question": "在2026年的人工智慧發展趨勢中，代理式AI的核心能力不包含下列哪一項？",
        "options": [
            "感知環境並收集資訊",
            "基於目標推理與決策",
            "自動生成視覺藝術創作",
            "反思並調整行動策略"
        ],
        "correct_answer_index": 2,
        "correct_answer_letter": "C",
        "topic": "生成式AI應用與規劃",
        "subtopic": "代理式AI",
        "concept": "代理式AI核心能力",
        "explanation": "代理式AI的核心能力通常包括感知環境、基於目標推理、行動執行與反思調整，不包含專門生成視覺藝術，該屬於生成式AI的特定應用。",
        "number": 1,
        "date": "2026-03-04"
    },
    {
        "question": "下列何者最符合2026年實體AI的應用場景？",
        "options": [
            "純虛擬虛擬助手系統",
            "自主載具的無人駕駛技術",
            "基於雲端的語音辨識系統",
            "網路數據分析平台"
        ],
        "correct_answer_index": 1,
        "correct_answer_letter": "B",
        "topic": "人工智慧基礎",
        "subtopic": "AI的定義與分類",
        "concept": "實體AI",
        "explanation": "實體AI指的是具實體行動能力的人工智慧系統，如機器人、自主載具等，純虛擬系統不屬於此範疇。",
        "number": 2,
        "date": "2026-03-04"
    },
    {
        "question": "在資料收集與分析流程中，ETL代表何種作業？",
        "options": [
            "資料抽取、轉換與載入",
            "資料加密、傳輸與保存",
            "資料視覺化、報告與回饋",
            "資料分群、建模與評估"
        ],
        "correct_answer_index": 0,
        "correct_answer_letter": "A",
        "topic": "資料處理與分析概念",
        "subtopic": "資料整理與分析流程",
        "concept": "ETL流程",
        "explanation": "ETL是資料工程中的抽取(Extract)、轉換(Transform)、載入(Load)三階段，是資料分析的重要前置步驟。",
        "number": 3,
        "date": "2026-03-04"
    },
    {
        "question": "在機器學習的三大類型中，以下哪一項不屬於其中之一？",
        "options": [
            "監督學習",
            "非監督學習",
            "集群學習",
            "強化學習"
        ],
        "correct_answer_index": 2,
        "correct_answer_letter": "C",
        "topic": "機器學習概念",
        "subtopic": "機器學習基本原理",
        "concept": "機器學習類型",
        "explanation": "機器學習主要分為監督學習、非監督學習及強化學習，集群學習並非正式類別。",
        "number": 4,
        "date": "2026-03-04"
    },
    {
        "question": "鑑別式AI與生成式AI的主要差異在於下列何者？",
        "options": [
            "鑑別式AI專注於辨識資料類別，生成式AI能創造新資料樣本",
            "生成式AI僅能辨識資料，鑑別式AI可生成圖像與文字",
            "鑑別式AI必須使用強化學習，生成式AI不需學習",
            "生成式AI能直接取代所有鑑別式AI功能"
        ],
        "correct_answer_index": 0,
        "correct_answer_letter": "A",
        "topic": "鑑別式 AI 與生成式 AI",
        "subtopic": "基本原理",
        "concept": "鑑別與生成模型差異",
        "explanation": "鑑別式AI側重於資料分類與辨識，生成式AI則用於創造新的資料樣本，例如圖像或文字。",
        "number": 5,
        "date": "2026-03-04"
    },
    {
        "question": "在資料隱私與安全的考量中，何者為資料保護的有效機制？",
        "options": [
            "公開所有資料以促進透明",
            "使用聯邦學習避免集中資料存取",
            "只用人工方式處理資料",
            "取消資料蒐集以防止任何風險"
        ],
        "correct_answer_index": 1,
        "correct_answer_letter": "B",
        "topic": "資料處理與分析概念",
        "subtopic": "資料隱私與安全",
        "concept": "聯邦學習",
        "explanation": "聯邦學習是一種分散式學習技術，可在保護資料隱私的前提下協同訓練模型，有效避免單點資料洩漏風險。",
        "number": 6,
        "date": "2026-03-04"
    },
    {
        "question": "下列何種機器學習模型屬於鑑別式模型？",
        "options": [
            "變分自編碼器（VAE）",
            "貝氏分類器（Naive Bayes）",
            "生成對抗網路（GAN）",
            "深度信念網路（DBN）"
        ],
        "correct_answer_index": 1,
        "correct_answer_letter": "B",
        "topic": "機器學習概念",
        "subtopic": "常見機器學習模型",
        "concept": "鑑別式模型",
        "explanation": "貝氏分類器是用於分類任務的鑑別式模型，而VAE與GAN屬於生成式模型。",
        "number": 7,
        "date": "2026-03-04"
    },
    {
        "question": "在生成式AI的應用中，何者是用於提升回應語境一致性的技術？",
        "options": [
            "剪枝技術",
            "即時推論技術",
            "檢索增強生成技術(RAG)",
            "正則化L2技術"
        ],
        "correct_answer_index": 2,
        "correct_answer_letter": "C",
        "topic": "生成式AI應用與規劃",
        "subtopic": "生成式AI技術",
        "concept": "語境一致性提升",
        "explanation": "檢索增強生成技術(RAG)結合外部知識庫檢索與生成模型，有助提升生成內容與上下文的一致性。",
        "number": 8,
        "date": "2026-03-04"
    },
    {
        "question": "何者為AI治理中，監理沙盒的主要功能？",
        "options": [
            "快速商業化AI產品，不受監管",
            "建立安全空間供AI技術測試與監管試驗",
            "封鎖所有新型AI應用以保護用戶",
            "完全開放AI資料公開分享"
        ],
        "correct_answer_index": 1,
        "correct_answer_letter": "B",
        "topic": "AI倫理與法規",
        "subtopic": "AI治理概念",
        "concept": "監理沙盒",
        "explanation": "監理沙盒為監管機構設置的安全測試環境，允許企業在受控條件下試驗新AI技術或產品，有助促進創新與合規。",
        "number": 9,
        "date": "2026-03-04"
    },
    {
        "question": "在深度學習中，何謂偏差變異權衡（Bias-Variance Tradeoff）？",
        "options": [
            "模型複雜度與訓練資料大小的比值",
            "偏差減少時變異必然增加的現象",
            "模型在訓練誤差與泛化能力間的平衡",
            "用於評估資料隱私風險的指標"
        ],
        "correct_answer_index": 2,
        "correct_answer_letter": "C",
        "topic": "機器學習概念",
        "subtopic": "機器學習基本原理",
        "concept": "偏差變異權衡",
        "explanation": "偏差變異權衡指的是模型需要在降低訓練誤差（偏差）與增強對未知資料泛化能力（變異）之間取得適當平衡。",
        "number": 10,
        "date": "2026-03-04"
    }
]